metacatalog/__init__.py
metacatalog/__main__.py
metacatalog/__version__.py
metacatalog/command_line.py
metacatalog/config.py
metacatalog/api/__init__.py
metacatalog/api/_mapping.py
metacatalog/api/add.py
metacatalog/api/catalog.py
metacatalog/api/db.py
metacatalog/api/find.py
metacatalog/api/io.py
metacatalog/api/show.py
metacatalog/cmd/__init__.py
metacatalog/cmd/_util.py
metacatalog/cmd/add.py
metacatalog/cmd/catalog.py
metacatalog/cmd/create.py
metacatalog/cmd/find.py
metacatalog/cmd/init.py
metacatalog/cmd/migration.py
metacatalog/cmd/populate.py
metacatalog/cmd/show.py
metacatalog/data/__init__.py
metacatalog/data/datasource_types.csv
metacatalog/data/datatypes.csv
metacatalog/data/entrygroup_types.csv
metacatalog/data/keywords.csv
metacatalog/data/licenses.csv
metacatalog/data/person_roles.csv
metacatalog/data/thesaurus.csv
metacatalog/data/units.csv
metacatalog/data/variables.csv
metacatalog/db/__init__.py
metacatalog/db/base.py
metacatalog/db/migration.py
metacatalog/db/session.py
metacatalog/db/revisions/__init__.py
metacatalog/db/revisions/rev0.py
metacatalog/db/revisions/rev1.py
metacatalog/db/revisions/rev10.py
metacatalog/db/revisions/rev11.py
metacatalog/db/revisions/rev12.py
metacatalog/db/revisions/rev13.py
metacatalog/db/revisions/rev14.py
metacatalog/db/revisions/rev15.py
metacatalog/db/revisions/rev2.py
metacatalog/db/revisions/rev3.py
metacatalog/db/revisions/rev4.py
metacatalog/db/revisions/rev5.py
metacatalog/db/revisions/rev6.py
metacatalog/db/revisions/rev7.py
metacatalog/db/revisions/rev8.py
metacatalog/db/revisions/rev9.py
metacatalog/ext/__init__.py
metacatalog/ext/base.py
metacatalog/ext/export/__init__.py
metacatalog/ext/export/extension.py
metacatalog/ext/io/__init__.py
metacatalog/ext/io/appender.py
metacatalog/ext/io/deleter.py
metacatalog/ext/io/extension.py
metacatalog/ext/io/importer.py
metacatalog/ext/io/interface.py
metacatalog/ext/io/reader.py
metacatalog/ext/standards_export/__init__.py
metacatalog-0.9.2.dist-info/LICENSE
metacatalog-0.9.2.dist-info/METADATA
metacatalog-0.9.2.dist-info/WHEEL
metacatalog-0.9.2.dist-info/entry_points.txt
metacatalog-0.9.2.dist-info/top_level.txt
metacatalog-0.9.2.dist-info/RECORD
