Metadata-Version: 2.1
Name: metacatalog
Version: 0.9.2
Summary: Metadata model management module.
Author: Mirko Mälicke
Author-email: mirko.maelicke@kit.edu
License: GPL v3
License-File: LICENSE
Requires-Dist: sqlalchemy <2.0
Requires-Dist: geoalchemy2
Requires-Dist: pandas <2.2
Requires-Dist: xarray
Requires-Dist: numpy
Requires-Dist: psycopg2-binary
Requires-Dist: tabulate
Requires-Dist: nltk
Requires-Dist: shapely
Requires-Dist: pyproj
Requires-Dist: requests
Requires-Dist: dicttoxml >=1.7.5
Requires-Dist: lxml
Requires-Dist: jinja2
Requires-Dist: tqdm
Requires-Dist: pydantic >=2.2.0
Requires-Dist: pydantic-settings
Requires-Dist: pydantic-geojson
Requires-Dist: python-dotenv
